MANIFEST.in
README.rst
setup.py
pytracremote/__init__.py
pytracremote/exceptions.py
pytracremote/trac_remote.py
pytracremote.egg-info/PKG-INFO
pytracremote.egg-info/SOURCES.txt
pytracremote.egg-info/dependency_links.txt
pytracremote.egg-info/not-zip-safe
pytracremote.egg-info/top_level.txt
pytracremote/scripts/tracremote.sh