Metadata-Version: 1.1
Name: pytracremote
Version: 0.0.3
Summary: Manager for multiple remote trac instances
Home-page: https://github.com/42cc/pytracremote
Author: 42coffeecups.com
Author-email: contact@42cc.co
License: UNKNOWN
Keywords: trac,ssh
Platform: UNKNOWN
Classifier: Programming Language :: Python
Classifier: Topic :: Software Development :: Libraries :: Python Modules
